bootstrap_pagination/__init__.py
bootstrap_pagination/locale/ru/LC_MESSAGES/django.mo
bootstrap_pagination/locale/ru/LC_MESSAGES/django.po
bootstrap_pagination/templates/bootstrap_pagination/pager.html
bootstrap_pagination/templates/bootstrap_pagination/pagination.html
bootstrap_pagination/templatetags/__init__.py
bootstrap_pagination/templatetags/bootstrap_pagination.py
django_bootstrap_pagination_nigelm-2.1.0.dist-info/METADATA
django_bootstrap_pagination_nigelm-2.1.0.dist-info/WHEEL
django_bootstrap_pagination_nigelm-2.1.0.dist-info/RECORD
